soika/.DS_Store
soika/__init__.py
soika/sample_data/gutcnina.graphml
soika/sample_data/sample_data.csv
soika/sample_data/sample_data.parquet
soika/sample_data/sample_data_geocoded.parquet
soika/sample_data/sample_data_geocoded_emotioned.parquet
soika/sample_data/sample_data_graph.graphml
soika/src/__init__.py
soika/src/geocoder/__init__.py
soika/src/geocoder/city_objects_extractor.py
soika/src/geocoder/geocoder.py
soika/src/geocoder/objects_address_extractor_by_rules.py
soika/src/geocoder/street_extractor.py
soika/src/geocoder/text_address_extractor_by_rules.py
soika/src/geocoder/word_form_matcher.py
soika/src/hyper_graph/hpgh.py
soika/src/risks/emotion_classifier.py
soika/src/risks/event_detector.py
soika/src/risks/regional_activity.py
soika/src/risks/text_classifier.py
soika/src/semantic_graph/__init__.py
soika/src/semantic_graph/g_attrs_adder.py
soika/src/semantic_graph/g_text_data_getter.py
soika/src/semantic_graph/keyword_extracter.py
soika/src/semantic_graph/semantic_closeness_annotator.py
soika/src/semantic_graph/semantic_graph_builder.py
soika/src/utils/constants.py
soika/src/utils/data_getter/__init__.py
soika/src/utils/data_getter/comments_reply_getter.py
soika/src/utils/data_getter/geo_data_getter.py
soika/src/utils/data_getter/historical_geo_data_getter.py
soika/src/utils/data_getter/location_getter.py
soika/src/utils/data_getter/street_getter.py
soika/src/utils/data_getter/vk_data_getter.py
soika/src/utils/data_preprocessing/__init__.py
soika/src/utils/data_preprocessing/preprocessor.py
soika/src/utils/data_processing/__init__.py
soika/src/utils/data_processing/area_matcher.py
soika/src/utils/data_processing/city_services_extract.py
soika/src/utils/data_processing/rule_for_natasha.py
soika/src/utils/exceptions/__init__.py
soika/src/utils/exceptions/custom_exceptions.py
soika/src/visual/__init__.py
soika/src/visual/graph_visualization.py
soika-0.3.0.2.dist-info/LICENSE.md
soika-0.3.0.2.dist-info/METADATA
soika-0.3.0.2.dist-info/WHEEL
soika-0.3.0.2.dist-info/RECORD
