Metadata-Version: 2.3
Name: soika
Version: 0.3.0.2
Summary: Library for city identity analysis from social media posts and comments
Author: sandrro
Requires-Python: >=3.10.6,<3.12
Classifier: Programming Language :: Python :: 3
Classifier: Programming Language :: Python :: 3.11
Provides-Extra: geocoder
Provides-Extra: vk-parser
Requires-Dist: flair (==0.15.1) ; extra == "geocoder"
Requires-Dist: geopandas (==0.14.4) ; extra == "geocoder"
Requires-Dist: geopy (==2.3.0) ; extra == "geocoder"
Requires-Dist: loguru (==0.7.2) ; extra == "geocoder"
Requires-Dist: natasha (==1.6.0) ; extra == "geocoder"
Requires-Dist: networkx (==3.3) ; extra == "geocoder"
Requires-Dist: nltk (==3.8.1) ; extra == "geocoder"
Requires-Dist: numpy (==1.25.2) ; extra == "geocoder"
Requires-Dist: osm2geojson (==0.2.3) ; extra == "geocoder"
Requires-Dist: osmapi (>=4.0.0,<5.0.0) ; extra == "geocoder"
Requires-Dist: osmnx (==1.5.1) ; extra == "geocoder"
Requires-Dist: pandarallel (==1.6.5) ; extra == "geocoder"
Requires-Dist: pandas (==2.2.2) ; extra == "geocoder" or extra == "vk-parser"
Requires-Dist: pymorphy2 (==0.9.1) ; extra == "geocoder"
Requires-Dist: rapidfuzz (>=3.9.0,<4.0.0) ; extra == "geocoder"
Requires-Dist: requests (>=2.28.0,<3.0.0) ; extra == "geocoder" or extra == "vk-parser"
Requires-Dist: shapely (==2.0.1) ; extra == "geocoder"
Requires-Dist: torch (>=2.6.0,<3.0.0) ; extra == "geocoder"
Requires-Dist: tqdm (==4.64.1) ; extra == "geocoder" or extra == "vk-parser"
